news_scraper_mcp/__init__.py
news_scraper_mcp/server.py
article_scraper_mcp-1.0.0.dist-info/METADATA
article_scraper_mcp-1.0.0.dist-info/WHEEL
article_scraper_mcp-1.0.0.dist-info/entry_points.txt
article_scraper_mcp-1.0.0.dist-info/licenses/LICENSE
article_scraper_mcp-1.0.0.dist-info/RECORD
